oxpecker/__init__.py
oxpecker/build.py
oxpecker/database.py
oxpecker/file.py
oxpecker/login.py
oxpecker/main.py
oxpecker/scan.py
oxpecker/serve.py
oxpecker/task.py
oxpecker/tunnel.py
oxpecker/utils.py
oxpecker/ws_oxpk.py
oxpecker/jsp-compiler/target/jsp-compiler-0.0.1-SNAPSHOT.jar
oxpecker/vendor/wstunnel
oxpecker-0.1.8.dist-info/METADATA
oxpecker-0.1.8.dist-info/WHEEL
oxpecker-0.1.8.dist-info/entry_points.txt
oxpecker-0.1.8.dist-info/top_level.txt
oxpecker-0.1.8.dist-info/RECORD
